yara_helper/__init__.py
yara_helper/parse.py
yara_helper-0.3.6.dist-info/LICENSE
yara_helper-0.3.6.dist-info/METADATA
yara_helper-0.3.6.dist-info/WHEEL
yara_helper-0.3.6.dist-info/top_level.txt
yara_helper-0.3.6.dist-info/RECORD
